mcp_word_document_typeset/__init__.py
mcp_word_document_typeset/main.py
mcp_word_document_typeset/tools.py
mcp_word_document_typeset/utils.py
mcp_word_document_typeset-1.0.0.dist-info/METADATA
mcp_word_document_typeset-1.0.0.dist-info/WHEEL
mcp_word_document_typeset-1.0.0.dist-info/entry_points.txt
mcp_word_document_typeset-1.0.0.dist-info/top_level.txt
mcp_word_document_typeset-1.0.0.dist-info/RECORD
