Metadata-Version: 2.4
Name: mcp-word-document-typeset
Version: 1.0.0
Summary: Word文档排版MCP服务
Author-email: Word MCP Services <support@example.com>
License: MIT
Requires-Python: >=3.10
Requires-Dist: python-docx>=1.1.0
Requires-Dist: fastmcp>=2.8.1
